{
  "BaseSaleAmount": 89.91826,
  "Taxes": [
    {
      "AdjustmentType": 0,
      "Billable": true,
      "CalculationType": 2,
      "CategoryDescription": "E-911 CHARGES",
      "CategoryID": 7,
      "CompanyIdentifier": "",
      "Compliance": false,
      "CustomerNumber": "",
      "Description": "E-911 Technical Charge",
      "ExemptionType": 0,
      "ExemptSaleAmount": 0,
      "InvoiceNumber": 0,
      "Optional": 0,
      "OptionalAlpha1": "",
      "Optional4": 0,
      "Optional5": 1,
      "Optional6": 0,
      "Optional7": 0,
      "Optional8": 0,
      "Optional9": 0,
      "Optional10": 0,
      "PCode": 4113900,
      "Rate": 0.05,
      "RefundUncollect": 0,
      "ServiceLevelNumber": 0,
      "Surcharge": false,
      "TaxableMeasure": 0,
      "TaxAmount": 0.05,
      "TaxLevel": 1,
      "TaxType": 264,
      "Lines": 0,
      "Minutes": 0,
      "OptionalFields": [
        {
          "OptionalKeyNo": 1,
          "OptionalValue": "AvaAfcTest Calculate Tax Inclusive Sales/Debit-Wireless "
        }
      ],
      "TransCharge": 89.91826
    },
    {
      "AdjustmentType": 0,
      "Billable": true,
      "CalculationType": 2,
      "CategoryDescription": "E-911 CHARGES",
      "CategoryID": 7,
      "CompanyIdentifier": "",
      "Compliance": true,
      "CustomerNumber": "",
      "Description": "E-911 Prepaid Wireless",
      "ExemptionType": 0,
      "ExemptSaleAmount": 0,
      "InvoiceNumber": 0,
      "Optional": 0,
      "OptionalAlpha1": "",
      "Optional4": 0,
      "Optional5": 1,
      "Optional6": 0,
      "Optional7": 0,
      "Optional8": 0,
      "Optional9": 0,
      "Optional10": 0,
      "PCode": 4132900,
      "Rate": 0.7,
      "RefundUncollect": 0,
      "ServiceLevelNumber": 0,
      "Surcharge": false,
      "TaxableMeasure": 0,
      "TaxAmount": 0.7,
      "TaxLevel": 2,
      "TaxType": 233,
      "Lines": 0,
      "Minutes": 0,
      "OptionalFields": [
        {
          "OptionalKeyNo": 1,
          "OptionalValue": "AvaAfcTest Calculate Tax Inclusive Sales/Debit-Wireless "
        }
      ],
      "TransCharge": 89.91826
    },
    {
      "AdjustmentType": 0,
      "Billable": true,
      "CalculationType": 2,
      "CategoryDescription": "E-911 CHARGES",
      "CategoryID": 7,
      "CompanyIdentifier": "",
      "Compliance": true,
      "CustomerNumber": "",
      "Description": "E-911 Prepaid Wireless",
      "ExemptionType": 0,
      "ExemptSaleAmount": 0,
      "InvoiceNumber": 0,
      "Optional": 0,
      "OptionalAlpha1": "",
      "Optional4": 0,
      "Optional5": 1,
      "Optional6": 0,
      "Optional7": 0,
      "Optional8": 0,
      "Optional9": 0,
      "Optional10": 0,
      "PCode": 4132900,
      "Rate": 0.25,
      "RefundUncollect": 0,
      "ServiceLevelNumber": 0,
      "Surcharge": false,
      "TaxableMeasure": 0,
      "TaxAmount": 0.25,
      "TaxLevel": 1,
      "TaxType": 233,
      "Lines": 0,
      "Minutes": 0,
      "OptionalFields": [
        {
          "OptionalKeyNo": 1,
          "OptionalValue": "AvaAfcTest Calculate Tax Inclusive Sales/Debit-Wireless "
        }
      ],
      "TransCharge": 89.91826
    },
    {
      "AdjustmentType": 0,
      "Billable": true,
      "CalculationType": 1,
      "CategoryDescription": "SALES AND USE TAXES",
      "CategoryID": 1,
      "CompanyIdentifier": "",
      "Compliance": true,
      "CustomerNumber": "",
      "Description": "Sales Tax",
      "ExemptionType": 0,
      "ExemptSaleAmount": 0,
      "InvoiceNumber": 0,
      "Optional": 0,
      "OptionalAlpha1": "",
      "Optional4": 0,
      "Optional5": 1,
      "Optional6": 0,
      "Optional7": 0,
      "Optional8": 0,
      "Optional9": 0,
      "Optional10": 0,
      "PCode": 4133800,
      "Rate": 0.036,
      "RefundUncollect": 0,
      "ServiceLevelNumber": 0,
      "Surcharge": false,
      "TaxableMeasure": 89.91826,
      "TaxAmount": 3.23705736,
      "TaxLevel": 3,
      "TaxType": 1,
      "Lines": 0,
      "Minutes": 0,
      "OptionalFields": [
        {
          "OptionalKeyNo": 1,
          "OptionalValue": "AvaAfcTest Calculate Tax Inclusive Sales/Debit-Wireless "
        }
      ],
      "TransCharge": 89.91826
    },
    {
      "AdjustmentType": 0,
      "Billable": true,
      "CalculationType": 1,
      "CategoryDescription": "SALES AND USE TAXES",
      "CategoryID": 1,
      "CompanyIdentifier": "",
      "Compliance": true,
      "CustomerNumber": "",
      "Description": "Sales Tax",
      "ExemptionType": 0,
      "ExemptSaleAmount": 0,
      "InvoiceNumber": 0,
      "Optional": 0,
      "OptionalAlpha1": "",
      "Optional4": 0,
      "Optional5": 1,
      "Optional6": 0,
      "Optional7": 0,
      "Optional8": 0,
      "Optional9": 0,
      "Optional10": 0,
      "PCode": 4133800,
      "Rate": 0.065,
      "RefundUncollect": 0,
      "ServiceLevelNumber": 0,
      "Surcharge": false,
      "TaxableMeasure": 89.91826,
      "TaxAmount": 5.8446869,
      "TaxLevel": 1,
      "TaxType": 1,
      "Lines": 0,
      "Minutes": 0,
      "OptionalFields": [
        {
          "OptionalKeyNo": 1,
          "OptionalValue": "AvaAfcTest Calculate Tax Inclusive Sales/Debit-Wireless "
        }
      ],
      "TransCharge": 89.91826
    }
  ]
}